README.md
setup.cfg
setup.py
aiobittrex/__init__.py
aiobittrex/bittrex.py
python_bittrex_aio.egg-info/PKG-INFO
python_bittrex_aio.egg-info/SOURCES.txt
python_bittrex_aio.egg-info/dependency_links.txt
python_bittrex_aio.egg-info/requires.txt
python_bittrex_aio.egg-info/top_level.txt