Metadata-Version: 1.1
Name: python-bittrex-aio
Version: 0.0.1
Summary: Asynchronous python bindings for bittrex API.
Home-page: https://github.com/BlockHub/python-bittrex-aio
Author: Karel L. Kubat
Author-email: karel@blockhub.nl
License: UNKNOWN
Platform: UNKNOWN
Classifier: Programming Language :: Python :: 3.6
Classifier: Operating System :: OS Independent
Classifier: Development Status :: 3 - Alpha
Classifier: Topic :: Office/Business :: Financial
